README.md
uxly_1shot_client/__init__.py
uxly_1shot_client/async_client.py
uxly_1shot_client/base.py
uxly_1shot_client/sync_client.py
uxly_1shot_client/validation.py
uxly_1shot_client/webhook.py
uxly_1shot_client/categories/contract_methods.py
uxly_1shot_client/categories/structs.py
uxly_1shot_client/categories/transactions.py
uxly_1shot_client/categories/wallets.py
uxly_1shot_client/models/common.py
uxly_1shot_client/models/contract_method.py
uxly_1shot_client/models/struct.py
uxly_1shot_client/models/transaction.py
uxly_1shot_client/models/wallet.py
uxly_1shot_client/models/webhooks.py
uxly_1shot_client-1.2.0.dist-info/METADATA
uxly_1shot_client-1.2.0.dist-info/WHEEL
uxly_1shot_client-1.2.0.dist-info/RECORD
