Metadata-Version: 2.4
Name: uxly-1shot-client
Version: 1.2.0
Summary: Python client for the 1Shot API
Project-URL: Homepage, https://github.com/uxly/1shot-clients
Project-URL: Documentation, https://github.com/uxly/1shot-clients/tree/main/clients/python
Project-URL: Repository, https://github.com/uxly/1shot-clients.git
Project-URL: Issues, https://github.com/uxly/1shot-clients/issues
Author-email: UXly <support@uxly.com>
License-Expression: MIT
Classifier: Development Status :: 4 - Beta
Classifier: Intended Audience :: Developers
Classifier: License :: OSI Approved :: MIT License
Classifier: Programming Language :: Python :: 3
Classifier: Programming Language :: Python :: 3.8
Classifier: Programming Language :: Python :: 3.9
Classifier: Programming Language :: Python :: 3.10
Classifier: Programming Language :: Python :: 3.11
Requires-Python: >=3.8
Requires-Dist: cryptography>=41.0.0
Requires-Dist: httpx>=0.24.0
Requires-Dist: pydantic>=2.0.0
Requires-Dist: requests>=2.31.0
